seriously/SeriouslyCommands.py
seriously/__init__.py
seriously/__main__.py
seriously/probably_prime.py
seriously/seriously.py
seriously/test/__init__.py
seriously/test/tests.py
seriouslylib/__init__.py
seriouslylib/cp437.py
seriouslylib/iterable.py
seriouslylib/nicenames.py
seriously-2.1.31.dist-info/LICENSE
seriously-2.1.31.dist-info/METADATA
seriously-2.1.31.dist-info/WHEEL
seriously-2.1.31.dist-info/RECORD
