Metadata-Version: 2.3
Name: seriously
Version: 2.1.31
Summary: A Python-based golfing language
License: MIT
Author: Mego
Requires-Python: >=3.12,<4.0
Classifier: License :: OSI Approved :: MIT License
Classifier: Programming Language :: Python :: 3
Classifier: Programming Language :: Python :: 3.12
Classifier: Programming Language :: Python :: 3.13
Requires-Dist: pycryptodome (>=3.21.0,<4.0.0)
